LICENSE.txt
MANIFEST.in
README.md
setup.py
/home/amine/Documents/projects/confluent-kafka-python/LICENSE.txt
/home/amine/Documents/projects/confluent-kafka-python/confluent_kafka/src/Admin.c
/home/amine/Documents/projects/confluent-kafka-python/confluent_kafka/src/AdminTypes.c
/home/amine/Documents/projects/confluent-kafka-python/confluent_kafka/src/Consumer.c
/home/amine/Documents/projects/confluent-kafka-python/confluent_kafka/src/Metadata.c
/home/amine/Documents/projects/confluent-kafka-python/confluent_kafka/src/Producer.c
/home/amine/Documents/projects/confluent-kafka-python/confluent_kafka/src/confluent_kafka.c
confluent_kafka/__init__.py
confluent_kafka/deserializing_consumer.py
confluent_kafka/error.py
confluent_kafka/serializing_producer.py
confluent_kafka/admin/__init__.py
confluent_kafka/avro/__init__.py
confluent_kafka/avro/cached_schema_registry_client.py
confluent_kafka/avro/error.py
confluent_kafka/avro/load.py
confluent_kafka/avro/serializer/__init__.py
confluent_kafka/avro/serializer/message_serializer.py
confluent_kafka/kafkatest/__init__.py
confluent_kafka/kafkatest/verifiable_client.py
confluent_kafka/kafkatest/verifiable_consumer.py
confluent_kafka/kafkatest/verifiable_producer.py
confluent_kafka/schema_registry/__init__.py
confluent_kafka/schema_registry/avro.py
confluent_kafka/schema_registry/error.py
confluent_kafka/schema_registry/json_schema.py
confluent_kafka/schema_registry/protobuf.py
confluent_kafka/schema_registry/schema_registry_client.py
confluent_kafka/serialization/__init__.py
confluent_kafka/src/Admin.c
confluent_kafka/src/AdminTypes.c
confluent_kafka/src/Consumer.c
confluent_kafka/src/Metadata.c
confluent_kafka/src/Producer.c
confluent_kafka/src/confluent_kafka.c
confluent_kafka/src/confluent_kafka.h
confluent_kafka_amine.egg-info/PKG-INFO
confluent_kafka_amine.egg-info/SOURCES.txt
confluent_kafka_amine.egg-info/dependency_links.txt
confluent_kafka_amine.egg-info/requires.txt
confluent_kafka_amine.egg-info/top_level.txt